mcp_server_ecs/__init__.py
mcp_server_ecs/main.py
mcp_server_ecs/common/__init__.py
mcp_server_ecs/common/client.py
mcp_server_ecs/common/errors.py
mcp_server_ecs/common/logs.py
mcp_server_ecs/conf/__init__.py
mcp_server_ecs/conf/config.py
mcp_server_ecs/tools/__init__.py
mcp_server_ecs/tools/event.py
mcp_server_ecs/tools/instance.py
mcp_server_ecs/tools/region.py
ecs_mcp_server-0.1.0.dist-info/METADATA
ecs_mcp_server-0.1.0.dist-info/WHEEL
ecs_mcp_server-0.1.0.dist-info/entry_points.txt
ecs_mcp_server-0.1.0.dist-info/top_level.txt
ecs_mcp_server-0.1.0.dist-info/RECORD
