Metadata-Version: 2.4
Name: ecs-mcp-server
Version: 0.1.0
Summary: Add your description here
Requires-Python: >=3.13
Requires-Dist: concurrent-log-handler>=0.9.25
Requires-Dist: dynaconf>=3.2.10
Requires-Dist: jsonref>=1.1.0
Requires-Dist: mcp[cli]>=1.6.0
Requires-Dist: pydantic>=2.11.3
Requires-Dist: volcengine-python-sdk>=1.1.5
